ansys/grantami/serverapi_openapi/__init__.py
ansys/grantami/serverapi_openapi/api/__init__.py
ansys/grantami/serverapi_openapi/api/aggregation_api.py
ansys/grantami/serverapi_openapi/api/data_api.py
ansys/grantami/serverapi_openapi/api/data_export_api.py
ansys/grantami/serverapi_openapi/api/database_api.py
ansys/grantami/serverapi_openapi/api/help_location_api.py
ansys/grantami/serverapi_openapi/api/integration_api.py
ansys/grantami/serverapi_openapi/api/job_queue_api.py
ansys/grantami/serverapi_openapi/api/license_api.py
ansys/grantami/serverapi_openapi/api/list_item_api.py
ansys/grantami/serverapi_openapi/api/list_management_api.py
ansys/grantami/serverapi_openapi/api/list_permissions_api.py
ansys/grantami/serverapi_openapi/api/metrics_api.py
ansys/grantami/serverapi_openapi/api/records___record_histories_api.py
ansys/grantami/serverapi_openapi/api/records___record_versions_api.py
ansys/grantami/serverapi_openapi/api/schema___attributes_api.py
ansys/grantami/serverapi_openapi/api/schema___configurations_api.py
ansys/grantami/serverapi_openapi/api/schema___constants_api.py
ansys/grantami/serverapi_openapi/api/schema___data_rules_api.py
ansys/grantami/serverapi_openapi/api/schema___databases_api.py
ansys/grantami/serverapi_openapi/api/schema___discrete_types___discrete_values_api.py
ansys/grantami/serverapi_openapi/api/schema___discrete_types_api.py
ansys/grantami/serverapi_openapi/api/schema___exporters_api.py
ansys/grantami/serverapi_openapi/api/schema___expressions_api.py
ansys/grantami/serverapi_openapi/api/schema___global_standard_names_api.py
ansys/grantami/serverapi_openapi/api/schema___help_files_api.py
ansys/grantami/serverapi_openapi/api/schema___home_pages_api.py
ansys/grantami/serverapi_openapi/api/schema___layout_sections_api.py
ansys/grantami/serverapi_openapi/api/schema___layouts_api.py
ansys/grantami/serverapi_openapi/api/schema___parameters_api.py
ansys/grantami/serverapi_openapi/api/schema___profile_tables_api.py
ansys_grantami_serverapi_openapi-4.0.1.dist-info/LICENSE
ansys_grantami_serverapi_openapi-4.0.1.dist-info/METADATA
ansys_grantami_serverapi_openapi-4.0.1.dist-info/WHEEL
ansys_grantami_serverapi_openapi-4.0.1.dist-info/RECORD
